BrainGenix/BG_API.py
BrainGenix/__init__.py
BrainGenix/EVM/__init__.py
BrainGenix/EVM/Debug/DoubleEcho.py
BrainGenix/EVM/Debug/Echo.py
BrainGenix/EVM/Debug/__init__.py
BrainGenix/LibUtils/ConfigCheck.py
BrainGenix/LibUtils/GetID.py
BrainGenix/NES/__init__.py
BrainGenix/NES/Client/Client.py
BrainGenix/NES/Client/Configuration.py
BrainGenix/NES/Client/RequestHandler.py
BrainGenix/NES/Client/__init__.py
BrainGenix/NES/Client/Authentication/Password.py
BrainGenix/NES/Client/Authentication/Token.py
BrainGenix/NES/Client/Authentication/__init__.py
BrainGenix/NES/Client/Modes/Local.py
BrainGenix/NES/Client/Modes/Remote.py
BrainGenix/NES/Client/Modes/__init__.py
BrainGenix/NES/Models/__init__.py
BrainGenix/NES/Models/Compartments/__init__.py
BrainGenix/NES/Models/Compartments/BS/BS.py
BrainGenix/NES/Models/Compartments/BS/Configuration.py
BrainGenix/NES/Models/Compartments/BS/__init__.py
BrainGenix/NES/Models/Compartments/SC/Configuration.py
BrainGenix/NES/Models/Compartments/SC/SC.py
BrainGenix/NES/Models/Compartments/SC/__init__.py
BrainGenix/NES/Models/Connections/__init__.py
BrainGenix/NES/Models/Connections/Receptor/Configuration.py
BrainGenix/NES/Models/Connections/Receptor/Receptor.py
BrainGenix/NES/Models/Connections/Receptor/__init__.py
BrainGenix/NES/Models/Connections/Staple/Configuration.py
BrainGenix/NES/Models/Connections/Staple/Staple.py
BrainGenix/NES/Models/Connections/Staple/__init__.py
BrainGenix/NES/Models/Neurons/__init__.py
BrainGenix/NES/Models/Neurons/BS/BSNeuron.py
BrainGenix/NES/Models/Neurons/BS/Configuration.py
BrainGenix/NES/Models/Neurons/BS/__init__.py
BrainGenix/NES/Models/Neurons/SC/Configuration.py
BrainGenix/NES/Models/Neurons/SC/SCNeuron.py
BrainGenix/NES/Models/Neurons/SC/__init__.py
BrainGenix/NES/Shapes/__init__.py
BrainGenix/NES/Shapes/Box/Box.py
BrainGenix/NES/Shapes/Box/Configuration.py
BrainGenix/NES/Shapes/Box/__init__.py
BrainGenix/NES/Shapes/Cylinder/Configuration.py
BrainGenix/NES/Shapes/Cylinder/Cylinder.py
pyBrainGenixClient-2024.4.29.dist-info/LICENSE.md
pyBrainGenixClient-2024.4.29.dist-info/METADATA
pyBrainGenixClient-2024.4.29.dist-info/WHEEL
pyBrainGenixClient-2024.4.29.dist-info/top_level.txt
pyBrainGenixClient-2024.4.29.dist-info/RECORD
