Metadata-Version: 2.1
Name: pyBrainGenixClient
Version: 2024.4.29
Summary: Python client for BrainGenix WBE platform.
Author-email: BrainGenix Team <braingenix@carboncopies.org>
Project-URL: Homepage, https://gitlab.braingenix.org/carboncopies/BrainGenix/NES/PythonClient
Project-URL: Bug Tracker, https://gitlab.braingenix.org/carboncopies/BrainGenix/NES/PythonClient/issues
Classifier: Programming Language :: Python :: 3
Classifier: License :: OSI Approved :: GNU Affero General Public License v3 or later (AGPLv3+)
Classifier: Operating System :: OS Independent
Requires-Python: >=3.7
License-File: LICENSE.md
Requires-Dist: requests
Requires-Dist: requests-futures
Requires-Dist: tqdm
Requires-Dist: yaspin
Requires-Dist: pillow
Requires-Dist: imageio
Requires-Dist: pandas
Requires-Dist: joblib
